{"name":"ingresar informacion de pago y continuar","id":"iniciar-sesion-en-la-aplicacion-de-saucedemo;ingresar-informacion-de-pago-y-continuar","testSteps":[{"number":1,"description":"Given que el usuario este en la pagina de informacion de checkout \"Checkout: Your Information\"","duration":228,"startTime":"2023-03-29T19:19:16.735265600-06:00[America/Regina]","screenshots":[{"screenshot":"57a5b6b05d4f7eeabcbeb68f8a8927458a4238281cbac698da2e702e53621e2a.png","timeStamp":1680139156963,"screenshotName":"57a5b6b05d4f7eeabcbeb68f8a8927458a4238281cbac698da2e702e53621e2a.png"}],"result":"SUCCESS","precondition":false,"level":0},{"number":2,"description":"When el usuario ingrese sus datos de compra","duration":470,"startTime":"2023-03-29T19:19:16.964990800-06:00[America/Regina]","screenshots":[{"screenshot":"c4434d93e9648ecc5ed865fb3ad85c05c4cd79c2daf7f98b54ed9c2f25bbee89.png","timeStamp":1680139157435,"screenshotName":"c4434d93e9648ecc5ed865fb3ad85c05c4cd79c2daf7f98b54ed9c2f25bbee89.png"}],"result":"SUCCESS","precondition":false,"level":0},{"number":3,"description":"And dar click en el boton de continue","duration":332,"startTime":"2023-03-29T19:19:17.438321300-06:00[America/Regina]","screenshots":[{"screenshot":"bb5ad1fe1614929a251f247fd8a394f6a918fd013e8f5e2ba83b540d190ab662.png","timeStamp":1680139157770,"screenshotName":"bb5ad1fe1614929a251f247fd8a394f6a918fd013e8f5e2ba83b540d190ab662.png"}],"result":"SUCCESS","precondition":false,"level":0},{"number":4,"description":"Then validamos que estemos en la pagina de overview \"Checkout: Overview\"","duration":231,"startTime":"2023-03-29T19:19:17.773035200-06:00[America/Regina]","screenshots":[{"screenshot":"bb5ad1fe1614929a251f247fd8a394f6a918fd013e8f5e2ba83b540d190ab662.png","timeStamp":1680139158004,"screenshotName":"bb5ad1fe1614929a251f247fd8a394f6a918fd013e8f5e2ba83b540d190ab662.png"}],"result":"SUCCESS","precondition":false,"level":0},{"number":5,"description":"And dar click en el boton de finish","duration":394,"startTime":"2023-03-29T19:19:18.006256600-06:00[America/Regina]","screenshots":[{"screenshot":"ce538becabb1e9720c383740ea1af2ab893ac658354fe1df26babc302006e31c.png","timeStamp":1680139158400,"screenshotName":"ce538becabb1e9720c383740ea1af2ab893ac658354fe1df26babc302006e31c.png"}],"result":"SUCCESS","precondition":false,"level":0}],"userStory":{"id":"iniciar-sesion-en-la-aplicacion-de-saucedemo","storyName":"iniciar sesion en la aplicacion de saucedemo","displayName":"iniciar sesion en la aplicacion de saucedemo","path":"test_login.feature","type":"feature","qualifiedTag":{"name":"iniciar sesion en la aplicacion de saucedemo","type":"feature","displayName":"iniciar sesion en la aplicacion de saucedemo"}},"featureTag":{"name":"iniciar sesion en la aplicacion de saucedemo","type":"feature","displayName":"iniciar sesion en la aplicacion de saucedemo"},"title":"ingresar informacion de pago y continuar","description":"","tags":[{"name":"IngresarInformacionCompra","type":"tag","displayName":"IngresarInformacionCompra"},{"name":"iniciar sesion en la aplicacion de saucedemo","type":"feature","displayName":"iniciar sesion en la aplicacion de saucedemo"}],"allTags":[{"name":"IngresarInformacionCompra","type":"tag","displayName":"IngresarInformacionCompra"},{"name":"iniciar sesion en la aplicacion de saucedemo","type":"feature","displayName":"iniciar sesion en la aplicacion de saucedemo"}],"startTime":"2023-03-29T19:19:16.728290100-06:00[America/Regina]","duration":1675,"projectKey":"","sessionId":"136df54ec38ad39400aecaf5f30f4103","driver":"chrome","isManualTestingUpToDate":false,"manual":false,"testSource":"Cucumber","result":"SUCCESS"}